TozaText/__init__.py
TozaText/core.py
TozaText/doc_modifier.py
TozaText/language_filter.py
TozaText/line_remover.py
TozaText/repetion.py
TozaText/tranlitrate.py
TozaText/unicode_reformattor.py
TozaText/url_remover.py
TozaText/utils/__init__.py
TozaText/utils/logging_utils.py
tozatext-0.1.7.dist-info/METADATA
tozatext-0.1.7.dist-info/WHEEL
tozatext-0.1.7.dist-info/RECORD
