Metadata-Version: 2.4
Name: TozaText
Version: 0.1.7
Summary: TozaText is a cleaning library for preprocessing raw Uzbek and multilingual text data.
Author-email: Shohrux Isakov <isakovsh19@gmail.com>
License: MIT
Requires-Python: >=3.10
Requires-Dist: datasets>=4.4.1
Requires-Dist: fasttext>=0.9.3
Requires-Dist: ftfy>=6.3.1
Requires-Dist: loguru>=0.7.0
Requires-Dist: pandas>=2.0.0
Requires-Dist: tqdm>=4.65.0
